{"cameraMode":{"drawMode":0,"name":"Shaded","section":"Shading Mode"},"sceneLighting":true,"audioPlay":false,"sceneViewState":{"m_AlwaysRefresh":false,"showFog":true,"showSkybox":true,"showFlares":true,"showImageEffects":true,"showParticleSystems":true,"showVisualEffectGraphs":true,"m_FxEnabled":true},"in2DMode":false,"pivot":{"x":470.8590087890625,"y":24.625,"z":508.04998779296877},"rotation":{"x":0.29573938250541689,"y":-0.5849496126174927,"z":0.27005425095558169,"w":0.7070313692092896},"size":14.168024063110352,"orthographic":true}